{
  "videoPath": "ansible_patch_id.mp4",
  "sessionTitle": "Ubuntu OS & Service patch management using Ansible",
  "speakers": [
    {
      "name": "Doni Kuswara",
      "bio": "Product Operations Engineer, PT. Biznet Gio Nusantara",
      "photoPath": "https://2021.ubucon.asia/sessions/ubuntu_os__service_patch_management_using_ansible/profile.jpg"
    }
  ],
  "sponsorsData":[
    {"class": "Diamond", "logos":[
      "https://2021.ubucon.asia/sponsors/ubuntu/logo.png"
    ]},
    {"class": "Gold", "logos":[
      "https://2021.ubucon.asia/sponsors/microsoft/logo.png"
    ]},
    {"class": "Silver", "logos":[
      "https://2021.ubucon.asia/sponsors/cloudmate/logo.png"
    ]}
  ]
}
